infiniguard_core/__init__.py
infiniguard_core/__version__.py
infiniguard_core/consts.py
infiniguard_core/credentials.py
infiniguard_core/ibox.py
infiniguard_core/logging/__init__.py
infiniguard_core/utils/__init__.py
infiniguard_core/utils/display.py
infiniguard_core-0.0.8.dist-info/METADATA
infiniguard_core-0.0.8.dist-info/WHEEL
infiniguard_core-0.0.8.dist-info/entry_points.txt
infiniguard_core-0.0.8.dist-info/namespace_packages.txt
infiniguard_core-0.0.8.dist-info/top_level.txt
infiniguard_core-0.0.8.dist-info/RECORD
